tuner/__init__.py
tuner/algorithms.py
tuner/analyser.py
tuner/configuration.py
tuner/inputs.py
tuner/notation.py
tuner/data/classic_intervals.yaml
tuner/data/persian_intervals_Shoor_Ebadi_1.yaml
tuner/gui/__init__.py
tuner/gui/analog_display.py
tuner/gui/app.py
tuner/gui/dbmeter.py
tuner/gui/spectrum.py
tuner/gui/tuner.kv
tuner/gui/styles/analog_display.kv
tuner/gui/styles/dbmeter.kv
tuner/gui/styles/spectrum.kv
tuner-1.0.0b2.dist-info/DESCRIPTION.rst
tuner-1.0.0b2.dist-info/METADATA
tuner-1.0.0b2.dist-info/RECORD
tuner-1.0.0b2.dist-info/WHEEL
tuner-1.0.0b2.dist-info/entry_points.txt
tuner-1.0.0b2.dist-info/metadata.json
tuner-1.0.0b2.dist-info/top_level.txt
