Metadata-Version: 2.0
Name: tuner
Version: 1.0.0b2
Summary: Musical instrument tuner using Kivy.
Home-page: http://github.com/pylover/tuner
Author: Vahid Mardani
Author-email: vahid.mardani@gmail.com
License: UNKNOWN
Platform: UNKNOWN
Requires-Dist: kivy
Requires-Dist: pymlconf
Requires-Dist: kivy
Requires-Dist: pyaudio
Requires-Dist: numpy
Requires-Dist: scipy
Requires-Dist: pygame
